{"title": "facter", "source": "gtfobins", "source_label": "GTFOBins", "path": "facter", "html": "<h1>facter</h1>\n<h2>Inherit</h2>\n<p><em>Context: sudo, unprivileged</em></p>\n<pre><code class=\"language-bash\">FACTERLIB=/path/to/dir/ facter</code></pre>\n<p><em>Context: sudo, unprivileged</em></p>\n<pre><code class=\"language-bash\">facter --custom-dir=/path/to/dir/ x</code></pre>\n", "excerpt": "facter Inherit Context: sudo, unprivileged FACTERLIB=/path/to/dir/ facter Context: sudo, unprivileged facter --custom-dir=/path/to/dir/ x", "tags": ["inherit"]}